CHANGES.txt
LICENSE.txt
MANIFEST.in
README.txt
setup.py
js/__init__.py
js.autobahn.egg-info/PKG-INFO
js.autobahn.egg-info/SOURCES.txt
js.autobahn.egg-info/dependency_links.txt
js.autobahn.egg-info/entry_points.txt
js.autobahn.egg-info/namespace_packages.txt
js.autobahn.egg-info/not-zip-safe
js.autobahn.egg-info/requires.txt
js.autobahn.egg-info/top_level.txt
js/autobahn/__init__.py
js/autobahn/test_autobahn|js.txt
js/autobahn/resources/README.txt
js/autobahn/resources/autobahn.js