Metadata-Version: 1.0
Name: js.autobahn
Version: 0.9.2-2
Summary: Fanstatic packaging of Autobahn|JS
Home-page: UNKNOWN
Author: Fanstatic Developers
Author-email: fanstatic@googlegroups.com
License: BSD
Platform: UNKNOWN
